proctools/cli/__init__.py
proctools/cli/_common.py
proctools/cli/logger.py
proctools/cli/status.py
proctools/products/__init__.py
proctools/products/adapters.py
proctools/products/dataproduct.py
proctools/products/depot.py
proctools/products/mixins.py
proctools/products/pancam/__init__.py
proctools/products/pancam/ancillary.py
proctools/products/pancam/mixins.py
proctools/products/pancam/observational.py
proctools/products/util.py
proctools-0.2.1.dist-info/LICENSE
proctools-0.2.1.dist-info/WHEEL
proctools-0.2.1.dist-info/METADATA
proctools-0.2.1.dist-info/RECORD
